[
  {
    "Time": "2025-01-10T12:03:22Z",
    "UserPrincipalName": "ap@contoso-industries.com",
    "Operation": "Set-Password",
    "InitiatedBy": "SelfService",
    "Comment": "Self-service password reset via portal"
  },
  {
    "Time": "2025-03-10T15:22:41Z",
    "UserPrincipalName": "ap@contoso-industries.com",
    "Operation": "Set-Password",
    "InitiatedBy": "Admin",
    "AdminId": "sec-analyst@contoso-industries.com",
    "Comment": "Forced reset after suspected mailbox compromise"
  },
  {
    "Time": "2025-03-10T15:25:03Z",
    "UserPrincipalName": "ap@contoso-industries.com",
    "Operation": "Update-MFA",
    "InitiatedBy": "Admin",
    "AdminId": "sec-analyst@contoso-industries.com",
    "Comment": "Enforced MFA for AP mailbox"
  }
]
